{
  "text": "@override\nWidget build(BuildContext _) => const FProgress();\n",
  "highlights": [],
  "links": [
    {
      "offset": 48,
      "length": 9,
      "url": "https://pub.dev/documentation/forui/0.17.0/forui.widgets.progress/FProgress/FProgress.html"
    }
  ],
  "tooltips": [
    {
      "offset": 48,
      "length": 9,
      "snippet": {
        "text": "FProgress({\n  FProgressStyle Function(FProgressStyle)? style,\n  String? semanticsLabel,\n  Key? key,\n})\n",
        "highlights": [],
        "links": [
          {
            "offset": 0,
            "length": 9,
            "url": "https://pub.dev/documentation/forui/0.17.0/forui.widgets.progress/FProgress/FProgress.html"
          },
          {
            "offset": 55,
            "length": 5,
            "url": "https://pub.dev/documentation/forui/0.17.0/forui.widgets.progress/FProgress/FProgress.html"
          },
          {
            "offset": 14,
            "length": 14,
            "url": "https://pub.dev/documentation/forui/0.17.0/forui.widgets.progress/FProgressStyle-class.html"
          },
          {
            "offset": 38,
            "length": 14,
            "url": "https://pub.dev/documentation/forui/0.17.0/forui.widgets.progress/FProgressStyle-class.html"
          },
          {
            "offset": 72,
            "length": 14,
            "url": "https://pub.dev/documentation/forui/0.17.0/forui.widgets.progress/FProgress/FProgress.html"
          },
          {
            "offset": 95,
            "length": 3,
            "url": "https://pub.dev/documentation/forui/0.17.0/forui.widgets.progress/FProgress/FProgress.html"
          }
        ],
        "tooltips": [],
        "container": {
          "name": "FProgress",
          "url": "https://pub.dev/documentation/forui/0.17.0/forui.widgets.progress/FProgress-class.html"
        }
      }
    }
  ]
}